chromedrivers/__init__.py
chromedrivers/chromedriver
chromedrivers/headless-chromium
py_seleniumdrivers_chromedrivers-1.0.2.data/scripts/download_drivers.sh
py_seleniumdrivers_chromedrivers-1.0.2.dist-info/LICENSE
py_seleniumdrivers_chromedrivers-1.0.2.dist-info/METADATA
py_seleniumdrivers_chromedrivers-1.0.2.dist-info/WHEEL
py_seleniumdrivers_chromedrivers-1.0.2.dist-info/top_level.txt
py_seleniumdrivers_chromedrivers-1.0.2.dist-info/RECORD
