Metadata-Version: 2.1
Name: py-seleniumdrivers-chromedrivers
Version: 1.0.2
Summary: AWS Lambda Chromedrivers
Home-page: https://github.com/AlexanderCollins/py-seleniumdrivers-chromedrivers
Author: Alexander Collins
Author-email: alex@freighty.net
License: UNKNOWN
Platform: UNKNOWN
Classifier: Programming Language :: Python :: 3
Classifier: License :: OSI Approved :: MIT License
Classifier: Operating System :: OS Independent
